googledrive/__init__.py
googledrive/_files.py
googledrive/_service.py
googledrive_files-0.1.1.dist-info/LICENSE
googledrive_files-0.1.1.dist-info/METADATA
googledrive_files-0.1.1.dist-info/WHEEL
googledrive_files-0.1.1.dist-info/top_level.txt
googledrive_files-0.1.1.dist-info/RECORD
