Metadata-Version: 2.1
Name: googledrive-files
Version: 0.1.1
Summary: Simple Google Drive API wrapper
Author-email: skitschy <s1kitschy@gmail.com>
Project-URL: Homepage, https://github.com/skitschy/pyGoogleDriveFiles
Project-URL: Documentation, https://googledrive-files.readthedocs.io/
Classifier: License :: OSI Approved :: MIT License
Classifier: Intended Audience :: Developers
Classifier: Operating System :: OS Independent
Classifier: Programming Language :: Python
Classifier: Programming Language :: Python :: 3
Classifier: Programming Language :: Python :: 3.5
Classifier: Programming Language :: Python :: 3.6
Classifier: Programming Language :: Python :: 3.7
Classifier: Programming Language :: Python :: 3.8
Classifier: Programming Language :: Python :: 3.9
Requires-Python: >=3.5
License-File: LICENSE
Requires-Dist: google-api-python-client
